sdb/__init__.py
sdb/main.py
py3_sdb-1.0.7.dist-info/LICENSE
py3_sdb-1.0.7.dist-info/METADATA
py3_sdb-1.0.7.dist-info/WHEEL
py3_sdb-1.0.7.dist-info/top_level.txt
py3_sdb-1.0.7.dist-info/RECORD
