Metadata-Version: 2.1
Name: py3-sdb
Version: 1.0.7
Summary: SDB is a simple database for beginners.
Home-page: https://github.com/DDavid701/sdb
Author: DDavid701
Author-email: ddavid701@gmail.com
Classifier: Programming Language :: Python :: 3
Classifier: License :: OSI Approved :: MIT License
Classifier: Operating System :: OS Independent
Requires-Python: >=3.10
License-File: LICENSE
